dictionary/__init__.py
dictionary/dictionary.py
an_extremely_simplistic_dictionary_kaa-3.0.1.dist-info/METADATA
an_extremely_simplistic_dictionary_kaa-3.0.1.dist-info/WHEEL
an_extremely_simplistic_dictionary_kaa-3.0.1.dist-info/top_level.txt
an_extremely_simplistic_dictionary_kaa-3.0.1.dist-info/RECORD
