Metadata-Version: 2.1
Name: an-extremely-simplistic-dictionary-kaa
Version: 3.0.1
Summary: UNKNOWN
Author: Kaan Atakan Aray
License: UNKNOWN
Platform: UNKNOWN
Requires-Python: >=3.8
Requires-Dist: requests (>=2.23.0)
